faker_microservice/__init__.py
faker_microservice-1.0.0.dist-info/LICENCE
faker_microservice-1.0.0.dist-info/METADATA
faker_microservice-1.0.0.dist-info/WHEEL
faker_microservice-1.0.0.dist-info/top_level.txt
faker_microservice-1.0.0.dist-info/RECORD
