Metadata-Version: 2.1
Name: faker-microservice
Version: 1.0.0
Summary: Provider for Faker which adds fake microservice names.
Home-page: https://github.com/craiga/faker-microservice
Author: Craig Anderson
Author-email: craiga@craiga.id.au
License: UNKNOWN
Platform: UNKNOWN
Classifier: Programming Language :: Python :: 3
Classifier: License :: OSI Approved :: MIT License
Classifier: Operating System :: OS Independent
Requires-Dist: faker
